{
  "id": "urn:ngsi-ld:plan:55761it5-3d4q-2321-p009-44bro198re0q",
  "name": "Sample Plan 1",
  "description": "Some description for sample plan 1",
  "validFor": {
    "startDateTime": "2025-01-01T00:00:00Z",
    "endDateTime": "2025-12-31T23:59:59Z"
  },
  "lifecycleStatus": "launched",
  "billCycleSpecification": {
    "billingPeriodLength": "1",
    "billingPeriodType": "MONTH",
    "billingPeriodEnd": "LAST_DAY_OF_CALENDAR_MONTH",
    "billingDateShift": "5",
    "paymentDueDateOffset": "15"
  },
  "subscriptionDurationLength": 6,
  "subscriptionDurationPeriodType": "MONTH",
  "agreements": [],
  "price": {
    "name": "Price components for Sample plan 1",
    "isBundle": true,
    "currency": "EUR",
    "bundleOp": "CUMULATIVE",
    "prices": [
      {
        "name": "Pre-paid Yearly Fee",
        "type": "ONE_TIME_PREPAID",
        "recurringChargePeriodLength": 1,
        "recurringChargePeriodType": "YEAR",
        "amount": 8000,
        "currency": "EUR",
        "ignore": false,
        "discount": {
          "name": "some discount",
          "isBundle": false,
          "computationBase": "parent-price",
          "percent": 20
        }
      },
      {
        "name": "Revenue on transactions",
        "type": "RECURRING_POSTPAID",
        "recurringChargePeriodLength": 1,
        "recurringChargePeriodType": "MONTH",
        "applicableBase": "bills-no-taxes",
        "applicableBaseReferencePeriod": "LAST_9_CHARGE_PERIODS",
        "computationBaseReferencePeriod": "CURRENT_CHARGE_PERIOD",
        "computationBase": "bills-no-taxes",
        "currency": "EUR",
        "ignore": false,
        "collapse": false,
        "isBundle": true,
        "bundleOp": "CUMULATIVE",
        "prices": [
          {
            "name": "tier 0: no revenue sharing for transactions below 100K",
            "amount": 0,
            "skipIfZero": false
          },
          {
            "name": "tier 1: 4% revenue sharing in the range 100-200K",
            "percent": 4,
            "discount": {
              "comment": "this is the 'min' of the tier x tier percentage",
              "amount": 4000
            },
            "resultingAmountRange": {
              "comment": "min is always zero. Max is the tier width x tier percentage (i.e. the max revenue for the tier window)",
              "min": 0,
              "max": 4000
            },
            "collapse": true,
            "skipIfZero": true
          },
          {
            "name": "tier 2: 3% revenue sharing in the range 200-500k",
            "percent": 3,
            "discount": {
              "name": "removing the lower part",
              "comment": "this is the 'min' of the tier x tier percentage",
              "amount": 6000
            },
            "resultingAmountRange": {
              "comment": "min is always zero. Max is the tier width x tier percentage (i.e. the max revenue for the tier window)",
              "min": 0,
              "max": 9000
            },
            "collapse": true
          },
          {
            "name": "tier 3: 2% revenue sharing in the range 500-800k",
            "percent": 2,
            "discount": {
              "name": "removing the lower part",
              "comment": "this is the 'min' of the tier x tier percentage",
              "amount": 10000
            },
            "resultingAmountRange": {
              "comment": "min is always zero. Max is the tier width x tier percentage (i.e. the max revenue for the tier window)",
              "min": 0,
              "max": 6000
            },
            "collapse": true
          },
          {
            "name": "tier 4: 1% revenue sharing for transactions above 800k",
            "percent": 1,
            "discount": {
              "name": "removing the lower part",
              "comment": "this is the 'min' of the tier x tier percentage",
              "amount": 8000
            },
            "resultingAmountRange": {
              "comment": "min is always zero. Max is the tier width x tier percentage (i.e. the max revenue for the tier window)",
              "min": 0
            },
            "collapse": true
          }

        ]


      },
      {
        "name": "Monthly postpaid fee....",
        "type": "RECURRING_POSTPAID",
        "recurringChargePeriodLength": 1,
        "recurringChargePeriodType": "MONTH",
        "amount": 150,
        "currency": "EUR",
        "ignore": false,
        "collapse": false,
        "discount": {
          "name": "discount for the first two month",
          "validPeriod": "FIRST_3_CHARGE_PERIOD",
          "computationBase": "parent-price",
          "percent": 90
        }
      }
    ]
  }
}